{
  "dataset": {
    "features": 4,
    "id": "iris",
    "instances": 122
  },
  "model": {
    "architecture": {
      "Activation": [
        "relu",
        "softmax"
      ],
      "Dense": [
        32,
        3
      ]
    },
    "hyperparameters": {
      "batch_size": 128,
      "epochs": 50,
      "loss": "categorical_crossentropy",
      "metrics": [
        "accuracy"
      ],
      "optimizer": "sgd",
      "type": "Sequential"
    }
  },
  "results": {
    "acc": 0.7857142686843872,
    "loss": 0.5538655519485474,
    "time": 0.47946392200037735
  }
}