{
  "dataset": {
    "features": 8,
    "id": "pima_indian_diabetes",
    "instances": 538
  },
  "model": {
    "architecture": {
      "Activation": [
        "hard_sigmoid",
        "softmax"
      ],
      "Dense": [
        32,
        2
      ]
    },
    "hyperparameters": {
      "batch_size": 64,
      "epochs": 100,
      "loss": "categorical_crossentropy",
      "metrics": [
        "accuracy"
      ],
      "optimizer": "nadam",
      "type": "Sequential"
    }
  },
  "results": {
    "acc": 0.6913043473077857,
    "loss": 0.5734304925669794,
    "time": 20.9112786882406
  }
}