{
  "dataset": {
    "features": 8,
    "id": "pima_indian_diabetes",
    "instances": 538
  },
  "model": {
    "architecture": {
      "Activation": [
        "hard_sigmoid",
        "softmax"
      ],
      "Dense": [
        64,
        2
      ]
    },
    "hyperparameters": {
      "batch_size": 16,
      "epochs": 10,
      "loss": "categorical_crossentropy",
      "metrics": [
        "accuracy"
      ],
      "optimizer": "adadelta",
      "type": "Sequential"
    }
  },
  "results": {
    "acc": 0.7391304347826086,
    "loss": 0.5771528210328973,
    "time": 7.525176807349908
  }
}