{
  "dataset": {
    "features": 8,
    "id": "pima_indian_diabetes",
    "instances": 538
  },
  "model": {
    "architecture": {
      "Activation": [
        "relu",
        "softmax"
      ],
      "Dense": [
        32,
        2
      ]
    },
    "hyperparameters": {
      "batch_size": 16,
      "epochs": 10,
      "loss": "categorical_crossentropy",
      "metrics": [
        "accuracy"
      ],
      "optimizer": "adagrad",
      "type": "Sequential"
    }
  },
  "results": {
    "acc": 0.32608695665131443,
    "loss": 10.862194732997729,
    "time": 5.127447519998896
  }
}