{
  "dataset": {
    "features": 8,
    "id": "pima_indian_diabetes",
    "instances": 538
  },
  "model": {
    "architecture": {
      "Activation": [
        "sigmoid",
        "softmax"
      ],
      "Dense": [
        32,
        2
      ]
    },
    "hyperparameters": {
      "batch_size": 128,
      "epochs": 20,
      "loss": "categorical_crossentropy",
      "metrics": [
        "accuracy"
      ],
      "optimizer": "rmsprop",
      "type": "Sequential"
    }
  },
  "results": {
    "acc": 0.6869565310685531,
    "loss": 0.5844667901163516,
    "time": 17.23430735399961
  }
}