{
  "dataset": {
    "features": 8,
    "id": "pima_indian_diabetes",
    "instances": 538
  },
  "model": {
    "architecture": {
      "Activation": [
        "relu",
        "softmax"
      ],
      "Dense": [
        64,
        2
      ]
    },
    "hyperparameters": {
      "batch_size": 32,
      "epochs": 10,
      "loss": "categorical_crossentropy",
      "metrics": [
        "accuracy"
      ],
      "optimizer": "rmsprop",
      "type": "Sequential"
    }
  },
  "results": {
    "acc": 0.6695652173913044,
    "loss": 0.8132449845257013,
    "time": 6.827754527999787
  }
}