{
  "dataset": {
    "features": 8,
    "id": "pima_indian_diabetes",
    "instances": 538
  },
  "model": {
    "architecture": {
      "Activation": [
        "hard_sigmoid",
        "softmax"
      ],
      "Dense": [
        32,
        2
      ]
    },
    "hyperparameters": {
      "batch_size": 32,
      "epochs": 20,
      "loss": "categorical_crossentropy",
      "metrics": [
        "accuracy"
      ],
      "optimizer": "adagrad",
      "type": "Sequential"
    }
  },
  "results": {
    "acc": 0.717391304347826,
    "loss": 0.5932928427405979,
    "time": 11.313861452039873
  }
}