{
  "dataset": {
    "features": 14,
    "id": "EEG_eye_state",
    "instances": 10486
  },
  "model": {
    "architecture": {
      "Activation": [
        "relu",
        "sigmoid"
      ],
      "Dense": [
        32,
        1
      ]
    },
    "hyperparameters": {
      "batch_size": 16,
      "epochs": 100,
      "loss": "binary_crossentropy",
      "metrics": [
        "accuracy"
      ],
      "optimizer": "sgd",
      "type": "Sequential"
    }
  },
  "results": {
    "acc": 0.4554962172580391,
    "loss": 8.680689207755252,
    "time": 111.25903466800003
  }
}