{
  "dataset": {
    "features": 14,
    "id": "EEG_eye_state",
    "instances": 10486
  },
  "model": {
    "architecture": {
      "Activation": [
        "relu",
        "sigmoid"
      ],
      "Dense": [
        64,
        1
      ]
    },
    "hyperparameters": {
      "batch_size": 128,
      "epochs": 10,
      "loss": "binary_crossentropy",
      "metrics": [
        "accuracy"
      ],
      "optimizer": "sgd",
      "type": "Sequential"
    }
  },
  "results": {
    "acc": 0.4554962172182497,
    "loss": 8.680689481082469,
    "time": 2.3374306830000933
  }
}