{
  "dataset": {
    "features": 8,
    "id": "pima_indian_diabetes",
    "instances": 538
  },
  "model": {
    "architecture": {
      "Activation": [
        "hard_sigmoid",
        "softmax"
      ],
      "Dense": [
        128,
        2
      ]
    },
    "hyperparameters": {
      "batch_size": 32,
      "epochs": 100,
      "loss": "categorical_crossentropy",
      "metrics": [
        "accuracy"
      ],
      "optimizer": "sgd",
      "type": "Sequential"
    }
  },
  "results": {
    "acc": 0.7260869565217392,
    "loss": 0.5825380296810814,
    "time": 19.956193288626764
  }
}